{
  "3": {
    "inputs": {
      "seed": 646056305492755,
      "steps": 20,
      "cfg": 1,
      "sampler_name": "euler",
      "scheduler": "simple",
      "denoise": 0.7500000000000001,
      "model": [
        "24",
        0
      ],
      "positive": [
        "15",
        0
      ],
      "negative": [
        "16",
        0
      ],
      "latent_image": [
        "23",
        0
      ]
    },
    "class_type": "KSampler",
    "_meta": {
      "title": "KSampler"
    }
  },
  "8": {
    "inputs": {
      "samples": [
        "3",
        0
      ],
      "vae": [
        "24",
        2
      ]
    },
    "class_type": "VAEDecode",
    "_meta": {
      "title": "VAE Decode"
    }
  },
  "15": {
    "inputs": {
      "clip_l": "A beautiful garden with colorful flowers and a gentle breeze. One girl stands in the center.Illustration_style",
      "t5xxl": "A beautiful garden with colorful flowers and a gentle breeze. One girl stands in the center.",
      "guidance": 3.5,
      "clip": [
        "24",
        1
      ]
    },
    "class_type": "CLIPTextEncodeFlux",
    "_meta": {
      "title": "CLIPTextEncodeFlux"
    }
  },
  "16": {
    "inputs": {
      "conditioning": [
        "15",
        0
      ]
    },
    "class_type": "ConditioningZeroOut",
    "_meta": {
      "title": "ConditioningZeroOut"
    }
  },
  "17": {
    "inputs": {
      "images": [
        "8",
        0
      ]
    },
    "class_type": "PreviewImage",
    "_meta": {
      "title": "Preview Image"
    }
  },
  "21": {
    "inputs": {
      "image": "ComfyUI_02059_.png"
    },
    "class_type": "LoadImage",
    "_meta": {
      "title": "Load Image"
    }
  },
  "23": {
    "inputs": {
      "pixels": [
        "21",
        0
      ],
      "vae": [
        "24",
        2
      ]
    },
    "class_type": "VAEEncode",
    "_meta": {
      "title": "VAE Encode"
    }
  },
  "24": {
    "inputs": {
      "ckpt_name": "flux1-dev-fp8.safetensors"
    },
    "class_type": "CheckpointLoaderSimple",
    "_meta": {
      "title": "Load Checkpoint"
    }
  }
}